LICENSE
README.rst
setup.py
judge0api/__init__.py
judge0api/client.py
judge0api/language.py
judge0api/status.py
judge0api/submission.py
judge0api.egg-info/PKG-INFO
judge0api.egg-info/SOURCES.txt
judge0api.egg-info/dependency_links.txt
judge0api.egg-info/requires.txt
judge0api.egg-info/top_level.txt