Metadata-Version: 2.1
Name: judge0api
Version: 0.1.20
Summary: A Python API for interacting with the Judge0 REST API
Home-page: https://github.com/vCra/judge0api
Author: Aaron Walker
Author-email: aaron@vcra.io
License: MIT
Platform: UNKNOWN
Classifier: Development Status :: 4 - Beta
Classifier: License :: OSI Approved :: MIT License
Classifier: Programming Language :: Python
Classifier: Programming Language :: Python :: 3
Classifier: Programming Language :: Python :: 3.6
Classifier: Programming Language :: Python :: 3.7
Classifier: Programming Language :: Python :: 3.8
License-File: LICENSE
